mediaconch/__init__.py
mediaconch/darwin/arm64/libmediaconch.0.dylib
mediaconch-22.3.dist-info/LICENSE
mediaconch-22.3.dist-info/METADATA
mediaconch-22.3.dist-info/WHEEL
mediaconch-22.3.dist-info/top_level.txt
mediaconch-22.3.dist-info/RECORD
