Metadata-Version: 2.1
Name: mediaconch
Version: 22.3
Summary: A python ctypes wrapper for mediaconch library.
Home-page: https://github.com/MediaArea/MediaConch_SourceCode
Author: MediaArea.Net
Author-email: info@mediaarea.net
License: BSD-2-Clause
Platform: UNKNOWN
Classifier: License :: OSI Approved :: BSD License
Classifier: Programming Language :: Python :: 3
Classifier: Development Status :: 5 - Production/Stable
Classifier: Operating System :: POSIX :: Linux
Classifier: Operating System :: MacOS :: MacOS X
Classifier: Topic :: Multimedia
Requires-Python: >=3.0
License-File: LICENSE
